pyspectools/__init__.py
pyspectools/spectrogram.py
py_spectrogram_tools-1.0.0.dist-info/LICENSE
py_spectrogram_tools-1.0.0.dist-info/METADATA
py_spectrogram_tools-1.0.0.dist-info/WHEEL
py_spectrogram_tools-1.0.0.dist-info/top_level.txt
py_spectrogram_tools-1.0.0.dist-info/RECORD
