Metadata-Version: 2.1
Name: py-spectrogram-tools
Version: 1.0.0
Summary: A library for recording and plotting spectrograms from audio data.
Author: Sviatoslav
Author-email: slawekzhukovski@gmail.com
License: MIT
Keywords: spectrogram audio analysis
Classifier: Programming Language :: Python :: 3
Classifier: License :: OSI Approved :: MIT License
Classifier: Operating System :: OS Independent
Requires-Python: >=3.6
License-File: LICENSE
Requires-Dist: matplotlib
Requires-Dist: sounddevice
